{"location":{"name":"Boston","region":"Lincolnshire","country":"United Kingdom","lat":53.1,"lon":-0.13,"tz_id":"Europe/London","localtime_epoch":1700990908,"localtime":"2023-11-26 9:28"},"current":{"last_updated_epoch":1700990100,"last_updated":"2023-11-26 09:15","temp_c":0.0,"temp_f":32.0,"is_day":1,"condition":{"text":"Overcast","icon":"//cdn.weatherapi.com/weather/64x64/day/122.png","code":1009},"wind_mph":3.8,"wind_kph":6.1,"wind_degree":190,"wind_dir":"S","pressure_mb":1016.0,"pressure_in":30.0,"precip_mm":0.0,"precip_in":0.0,"humidity":100,"cloud":100,"feelslike_c":-2.8,"feelslike_f":26.9,"vis_km":10.0,"vis_miles":6.0,"uv":1.0,"gust_mph":8.4,"gust_kph":13.6}}